MANIFEST.in
setup.py
gradiop/__init__.py
gradiop/plug.py
gradiop/version.py
gradiop.egg-info/PKG-INFO
gradiop.egg-info/SOURCES.txt
gradiop.egg-info/dependency_links.txt
gradiop.egg-info/entry_points.txt
gradiop.egg-info/requires.txt
gradiop.egg-info/top_level.txt
gradiop/templates/cdn/favicon.png
gradiop/templates/cdn/gradio.js
gradiop/templates/cdn/index.html
gradiop/templates/cdn/index.html1
gradiop/templates/cdn/assets/BlockLabel-1f250d5e.js
gradiop/templates/cdn/assets/BlockLabel-1f250d5e.js.map
gradiop/templates/cdn/assets/BlockTitle-9526a5ec.js
gradiop/templates/cdn/assets/BlockTitle-9526a5ec.js.map
gradiop/templates/cdn/assets/Blocks-005a10ea.css
gradiop/templates/cdn/assets/Blocks-cda355f2.js
gradiop/templates/cdn/assets/Blocks-cda355f2.js.map
gradiop/templates/cdn/assets/Button-4cd12e76.css
gradiop/templates/cdn/assets/Button-6ea4ac43.js
gradiop/templates/cdn/assets/Button-6ea4ac43.js.map
gradiop/templates/cdn/assets/ColorPicker-25010187.css
gradiop/templates/cdn/assets/ColorPicker.svelte_svelte_type_style_lang-5b5db9d3.js.map
gradiop/templates/cdn/assets/Column-2853eb31.css
gradiop/templates/cdn/assets/Column-cf8162c7.js
gradiop/templates/cdn/assets/Column-cf8162c7.js.map
gradiop/templates/cdn/assets/Column.svelte_svelte_type_style_lang-bf454eb5.js.map
gradiop/templates/cdn/assets/Copy-cd6d6056.js
gradiop/templates/cdn/assets/Copy-cd6d6056.js.map
gradiop/templates/cdn/assets/Download-e1dbb2d4.js
gradiop/templates/cdn/assets/Download-e1dbb2d4.js.map
gradiop/templates/cdn/assets/DropdownArrow-5fa4dd09.css
gradiop/templates/cdn/assets/DropdownArrow.svelte_svelte_type_style_lang-109ebd5a.js.map
gradiop/templates/cdn/assets/Empty-0c822ba8.js
gradiop/templates/cdn/assets/Empty-0c822ba8.js.map
gradiop/templates/cdn/assets/File-19deefb1.js
gradiop/templates/cdn/assets/File-19deefb1.js.map
gradiop/templates/cdn/assets/Form-189d7bad.css
gradiop/templates/cdn/assets/Form-54da9211.js
gradiop/templates/cdn/assets/Form-54da9211.js.map
gradiop/templates/cdn/assets/Image-003ee87c.css
gradiop/templates/cdn/assets/Image-065ab840.js
gradiop/templates/cdn/assets/Image-065ab840.js.map
gradiop/templates/cdn/assets/Image-3059c7c5.js
