Metadata-Version: 2.1
Name: gradiop
Version: 0.0.7
Summary: gradio 本地部署 插件
Home-page: https://gitee.com/zhys513/gradio_plug
Author: zhys513
Author-email: 254851907@qq.com
License: UNKNOWN
Platform: UNKNOWN
Requires-Python: >=3.6
